omicscope/__init__.py
omicscope/__main__.py
omicscope/cli.py
omicscope/EnrichmentAnalysis/EnrichmentVisualization.py
omicscope/EnrichmentAnalysis/GSEA.py
omicscope/EnrichmentAnalysis/ORA.py
omicscope/EnrichmentAnalysis/__init__.py
omicscope/General/GeneralVisualization.py
omicscope/General/Omicscope.py
omicscope/General/Snapshot.py
omicscope/General/__init__.py
omicscope/General/Input/DIANN.py
omicscope/General/Input/FragPipe.py
omicscope/General/Input/General.py
omicscope/General/Input/MaxQuant.py
omicscope/General/Input/PatternLab.py
omicscope/General/Input/Progenesis.py
omicscope/General/Input/ProteomeDiscoverer.py
omicscope/General/Input/RPKM.py
omicscope/General/Input/__init__.py
omicscope/General/Stats/Longitudinal_Stat.py
omicscope/General/Stats/Performed_Stat.py
omicscope/General/Stats/Static_Statistics.py
omicscope/General/Stats/Statistic_Module.py
omicscope/General/Stats/contaminants.csv
omicscope/General/Stats/imputation.py
omicscope/General/Stats/normalization.py
omicscope/MultipleData/MultipleVisualization.py
omicscope/MultipleData/Nebula.py
omicscope/MultipleData/__init__.py
omicscope-1.5.0.dist-info/AUTHORS.rst
omicscope-1.5.0.dist-info/LICENSE
omicscope-1.5.0.dist-info/METADATA
omicscope-1.5.0.dist-info/WHEEL
omicscope-1.5.0.dist-info/entry_points.txt
omicscope-1.5.0.dist-info/top_level.txt
omicscope-1.5.0.dist-info/RECORD
