Metadata-Version: 2.1
Name: omicscope
Version: 1.5.0
Summary: OmicScope: from quantitative proteomics to systems biology.
Home-page: https://github.com/guireiso/omicscope
Author: Guilherme Reis-de-Oliveira
Author-email: guioliveirareis@gmail.com
License: MIT
Project-URL: Documentation, https://omicscope.readthedocs.io/
Project-URL: Changelog, https://omicscope.readthedocs.io/en/latest/changelog.html
Project-URL: Issue Tracker, https://github.com/guireiso/omicscope/issues
Keywords: Proteomics,Omics,Differential Expression,Systems Biology
Classifier: Development Status :: 5 - Production/Stable
Classifier: Intended Audience :: Developers
Classifier: License :: OSI Approved :: MIT License
Classifier: Operating System :: Unix
Classifier: Operating System :: POSIX
Classifier: Operating System :: Microsoft :: Windows
Classifier: Programming Language :: Python
Classifier: Programming Language :: Python :: 3 :: Only
Classifier: Programming Language :: Python :: 3.8
Classifier: Programming Language :: Python :: 3.9
Classifier: Programming Language :: Python :: 3.10
Classifier: Programming Language :: Python :: 3.11
Classifier: Topic :: Utilities
Requires-Python: >=3.7
License-File: LICENSE
License-File: AUTHORS.rst
Requires-Dist: setuptools >=30.3.0
Requires-Dist: wheel
Requires-Dist: adjustText ==0.8
Requires-Dist: altair ==4.2.0
Requires-Dist: flake8 ==6.0.0
Requires-Dist: gseapy ==1.0.6
Requires-Dist: kneed ==0.8.1
Requires-Dist: matplotlib ==3.6.2
Requires-Dist: matplotlib-inline ==0.1.6
Requires-Dist: networkx ==2.8.8
Requires-Dist: numpy ==1.23.4
Requires-Dist: openpyxl ==3.0.10
Requires-Dist: packaging ==21.3
Requires-Dist: pandas ==1.5.1
Requires-Dist: pkginfo ==1.9.4
Requires-Dist: pycirclize ==0.4.0
Requires-Dist: scikit-learn ==1.1.3
Requires-Dist: scipy ==1.9.3
Requires-Dist: seaborn ==0.12.1
Requires-Dist: statsmodels ==0.13.5
Requires-Dist: tox ==3.27.0
Requires-Dist: sphinx-rtd-theme
Requires-Dist: UpSetPlot ==0.6.1
Requires-Dist: xlrd ==2.0.1
Requires-Dist: zipp ==3.11.0
